stratis_webservice/__init__.py
stratis_webservice/decorators.py
stratis_webservice/helpers.py
stratis_webservice/templates.py
stratis_webservice/templates_test.py
stratis_webservice/webserver.py
stratis_webservice/webservice.py
stratis_webservice-0.2.24.dist-info/METADATA
stratis_webservice-0.2.24.dist-info/WHEEL
stratis_webservice-0.2.24.dist-info/top_level.txt
stratis_webservice-0.2.24.dist-info/RECORD
