Metadata-Version: 2.1
Name: stratis-webservice
Version: 0.2.24
Summary: A simple web template engine for fast api's and websites. Very low memory and cpu print that fits docker and kubernetes pods, or can run parallel to your application
Home-page: https://github.com/LamaAni/stratis
Author: Zav Shotan
Author-email: 
License: LICENSE
Platform: any
Requires-Python: >=3.6
Requires-Dist: match-pattern
Requires-Dist: zthreading
Requires-Dist: TicTocTimer
Requires-Dist: zcommon
Requires-Dist: jinja2
Requires-Dist: sanic
